Metadata-Version: 2.1
Name: sphinx-pytype-substitution
Version: 0.1.1
Summary: auto substitution for python types like modules, classes and functions (created by auxilium)
Home-page: https://github.com/sonntagsgesicht/sphinx-pytype-substitution
Author: sonntagsgesicht
Author-email: sonntagsgesicht@icloud.com
License: Apache License 2.0
Platform: any
Classifier: Development Status :: 3 - Alpha
Classifier: Intended Audience :: Education
Classifier: Intended Audience :: Developers
Classifier: License :: OSI Approved :: Apache Software License
Classifier: Operating System :: OS Independent
Classifier: Programming Language :: Python
Classifier: Programming Language :: Python :: 3
Classifier: Programming Language :: Python :: 3.7
Classifier: Programming Language :: Python :: 3.8
Classifier: Programming Language :: Python :: 3.9
Classifier: Programming Language :: Python :: 3.10
Classifier: Topic :: Education
Classifier: Topic :: Software Development
License-File: LICENSE
